qcinfo/__init__.py
qcinfo/cli.py
qcinfo-1.0.8.dist-info/LICENSE
qcinfo-1.0.8.dist-info/METADATA
qcinfo-1.0.8.dist-info/WHEEL
qcinfo-1.0.8.dist-info/entry_points.txt
qcinfo-1.0.8.dist-info/top_level.txt
qcinfo-1.0.8.dist-info/RECORD
